LICENSE
README.md
setup.cfg
setup.py
Open_LISA_SDK/__init__.py
Open_LISA_SDK.egg-info/PKG-INFO
Open_LISA_SDK.egg-info/SOURCES.txt
Open_LISA_SDK.egg-info/dependency_links.txt
Open_LISA_SDK.egg-info/requires.txt
Open_LISA_SDK.egg-info/top_level.txt
Open_LISA_SDK/common/__init__.py
Open_LISA_SDK/common/protocol/__init__.py
Open_LISA_SDK/common/protocol/message_protocol.py
Open_LISA_SDK/common/protocol/message_protocol_rs232.py
Open_LISA_SDK/common/protocol/message_protocol_tcp.py
Open_LISA_SDK/common/utils/__init__.py
Open_LISA_SDK/common/utils/bytes.py
Open_LISA_SDK/domain/__init__.py
Open_LISA_SDK/domain/decorators/__init__.py
Open_LISA_SDK/domain/decorators/message_protocol_track.py
Open_LISA_SDK/domain/decorators/with_lock.py
Open_LISA_SDK/domain/exceptions/__init__.py
Open_LISA_SDK/domain/exceptions/could_not_connect_to_server.py
Open_LISA_SDK/domain/exceptions/invalid_command.py
Open_LISA_SDK/domain/exceptions/invalid_path_exception.py
Open_LISA_SDK/domain/exceptions/sdk_exception.py
Open_LISA_SDK/domain/protocol/__init__.py
Open_LISA_SDK/domain/protocol/client_protocol.py
Open_LISA_SDK/logging/__init__.py
Open_LISA_SDK/logging/log.py
Open_LISA_SDK/tests/__init__.py
Open_LISA_SDK/tests/test_integration_with_server.py