Metadata-Version: 2.1
Name: Open-LISA-SDK
Version: 1.1.4
Summary: SDK for Laboratory Instrument Station Adapter
Home-page: https://github.com/aalvarezwindey/Open-LISA-SDK
Download-URL: https://github.com/aalvarezwindey/Open-LISA-SDK/archive/refs/tags/1.1.4.tar.gz
Author: Ariel Alvarez Windey & Gabriel Robles
Author-email: ajalvarez@fi.uba.ar
License: MIT
Keywords: SDK,ELECTRONIC,INSTRUMENT,ADAPTER,FIUBA,OPEN,LISA,LABORATORY
Classifier: Development Status :: 4 - Beta
Classifier: Intended Audience :: Developers
Classifier: Topic :: Software Development :: Build Tools
Classifier: License :: OSI Approved :: MIT License
Classifier: Programming Language :: Python :: 3.6
License-File: LICENSE
